AUTHORS
LICENSE
MANIFEST.in
README.rst
TODO.rst
setup.py
django_news.egg-info/PKG-INFO
django_news.egg-info/SOURCES.txt
django_news.egg-info/dependency_links.txt
django_news.egg-info/top_level.txt
news/__init__.py
news/admin.py
news/constants.py
news/exceptions.py
news/models.py
news/urls.py
news/views.py
news/fixtures/news_test_data.json
news/management/__init__.py
news/management/commands/__init__.py
news/management/commands/process_news_feeds.py
news/management/commands/purge_articles.py
news/migrations/0001_initial.py
news/migrations/__init__.py
news/news_tests/__init__.py
news/news_tests/models.py
news/news_tests/tests.py
news/news_tests/urls.py
news/templates/base.html
news/templates/news/article_list.html